ble2wled/__init__.py
ble2wled/animation.py
ble2wled/cli_simulator.py
ble2wled/colors.py
ble2wled/config.py
ble2wled/main.py
ble2wled/mqtt.py
ble2wled/simulator.py
ble2wled/states.py
ble2wled/wled.py
ble2wled-1.0.1.dist-info/METADATA
ble2wled-1.0.1.dist-info/WHEEL
ble2wled-1.0.1.dist-info/entry_points.txt
ble2wled-1.0.1.dist-info/licenses/LICENSE
ble2wled-1.0.1.dist-info/RECORD
