Metadata-Version: 2.4
Name: ble2wled
Version: 1.0.1
Summary: Real-time Bluetooth Low Energy beacon visualization on WLED LED strips
Project-URL: Homepage, https://ble2wled.tobotec.ch
Project-URL: Repository, https://github.com/tobus3000/ble2wled
Project-URL: Issues, https://github.com/tobus3000/ble2wled/issues
Author-email: Tobias Hildebrand <tobus3000@tobotec.ch>
License: MIT
License-File: LICENSE
Keywords: beacon,ble,bluetooth,leds,mqtt,wled
Classifier: Development Status :: 5 - Production/Stable
Classifier: Intended Audience :: Developers
Classifier: License :: OSI Approved :: MIT License
Classifier: Operating System :: OS Independent
Classifier: Programming Language :: Python :: 3
Classifier: Programming Language :: Python :: 3.10
Classifier: Programming Language :: Python :: 3.11
Classifier: Programming Language :: Python :: 3.12
Classifier: Programming Language :: Python :: 3.13
Classifier: Programming Language :: Python :: 3.14
Classifier: Topic :: Home Automation
Classifier: Topic :: Software Development :: Libraries :: Python Modules
Requires-Python: >=3.10
Requires-Dist: paho-mqtt>=1.6.0
Requires-Dist: python-dotenv>=1.0.0
Requires-Dist: requests>=2.25.0
Provides-Extra: dev
Requires-Dist: git-cliff>=0.25.0; extra == 'dev'
Requires-Dist: myst-parser>=0.17.0; extra == 'dev'
Requires-Dist: pytest-cov>=3.0.0; extra == 'dev'
Requires-Dist: pytest>=7.0.0; extra == 'dev'
Requires-Dist: ruff>=0.1.0; extra == 'dev'
Requires-Dist: sphinx-rtd-theme>=1.0.0; extra == 'dev'
Requires-Dist: sphinx>=4.5.0; extra == 'dev'
